setup.cfg
setup.py
aws_lambda_configurer/__init__.py
aws_lambda_configurer.egg-info/PKG-INFO
aws_lambda_configurer.egg-info/SOURCES.txt
aws_lambda_configurer.egg-info/dependency_links.txt
aws_lambda_configurer.egg-info/entry_points.txt
aws_lambda_configurer.egg-info/requires.txt
aws_lambda_configurer.egg-info/top_level.txt
aws_lambda_configurer.egg-info/zip-safe