Metadata-Version: 1.1
Name: aws-lambda-configurer
Version: 0.1.0
Summary: aws-lambda-configurer - Resolve AWS lambda configuration from description field and other sources (e.g. s3)
Home-page: https://github.com/Immobilienscout24/aws-lambda-configurer
Author: Jens Zastrow
Author-email: jens.zastrow_external@immobilienscout24.de
License: APACHE LICENSE, VERSION 2.0
Platform: UNKNOWN
Classifier: Development Status :: 4 - Beta
Classifier: Environment :: Console
Classifier: Intended Audience :: Developers
Classifier: Intended Audience :: System Administrators
Classifier: License :: OSI Approved :: Apache Software License
Classifier: Programming Language :: Python
Classifier: Topic :: System :: Systems Administration
